picohost/__init__.py
picohost/base.py
picohost/flash_picos.py
picohost/motor.py
picohost/testing.py
picohost-0.0.2.dist-info/METADATA
picohost-0.0.2.dist-info/WHEEL
picohost-0.0.2.dist-info/entry_points.txt
picohost-0.0.2.dist-info/top_level.txt
picohost-0.0.2.dist-info/RECORD
