Metadata-Version: 2.4
Name: picohost
Version: 0.0.2
Summary: Host control and management tools for Raspberry Pi Pico devices
Author-email: Christian Hellum Bye <cbh@berkeley.edu>
License: MIT
Classifier: Intended Audience :: Developers
Classifier: License :: OSI Approved :: MIT License
Classifier: Programming Language :: Python :: 3
Classifier: Topic :: Software Development :: Embedded Systems
Classifier: Topic :: System :: Hardware
Requires-Python: >=3.9
Requires-Dist: numpy
Requires-Dist: pyserial
Provides-Extra: dev
Requires-Dist: build; extra == "dev"
Requires-Dist: twine; extra == "dev"
Requires-Dist: black; extra == "dev"
Requires-Dist: flake8; extra == "dev"
Requires-Dist: pytest; extra == "dev"
Requires-Dist: pytest-cov; extra == "dev"
Requires-Dist: pytest-timeout; extra == "dev"
Requires-Dist: pyserial-mock; extra == "dev"
